AUTHORS.rst
CONTRIBUTING.rst
HISTORY.rst
LICENSE
MANIFEST.in
README.rst
setup.py
data_dispenser/__init__.py
data_dispenser/sources.py
data_dispenser.egg-info/PKG-INFO
data_dispenser.egg-info/SOURCES.txt
data_dispenser.egg-info/dependency_links.txt
data_dispenser.egg-info/not-zip-safe
data_dispenser.egg-info/requires.txt
data_dispenser.egg-info/top_level.txt