Metadata-Version: 1.1
Name: data_dispenser
Version: 0.2.5.1
Summary: Loads data from various formats
Home-page: https://github.com/catherinedevlin/data_dispenser
Author: Catherine Devlin
Author-email: catherine.devlin@gmail.com
License: MIT
Keywords: data_dispenser
Platform: UNKNOWN
Classifier: Development Status :: 2 - Pre-Alpha
Classifier: Intended Audience :: Developers
Classifier: License :: OSI Approved :: MIT License
Classifier: Natural Language :: English
Classifier: Programming Language :: Python :: 3
Classifier: Programming Language :: Python :: 3.4
